Cellan/__init__.py
Cellan/__main__.py
Cellan/analyzer.py
Cellan/detector.py
Cellan/detectors/__init__.py
Cellan/detectron2/_C.cp310-win_amd64.pyd
Cellan/detectron2/_C.cp39-win_amd64.pyd
Cellan/detectron2/__init__.py
Cellan/detectron2/checkpoint/__init__.py
Cellan/detectron2/checkpoint/c2_model_loading.py
Cellan/detectron2/checkpoint/catalog.py
Cellan/detectron2/checkpoint/detection_checkpoint.py
Cellan/detectron2/config/__init__.py
Cellan/detectron2/config/compat.py
Cellan/detectron2/config/config.py
Cellan/detectron2/config/defaults.py
Cellan/detectron2/config/instantiate.py
Cellan/detectron2/config/lazy.py
Cellan/detectron2/data/__init__.py
Cellan/detectron2/data/benchmark.py
Cellan/detectron2/data/build.py
Cellan/detectron2/data/catalog.py
Cellan/detectron2/data/common.py
Cellan/detectron2/data/dataset_mapper.py
Cellan/detectron2/data/datasets/__init__.py
Cellan/detectron2/data/datasets/builtin.py
Cellan/detectron2/data/datasets/builtin_meta.py
Cellan/detectron2/data/datasets/cityscapes.py
Cellan/detectron2/data/datasets/cityscapes_panoptic.py
Cellan/detectron2/data/datasets/coco.py
Cellan/detectron2/data/datasets/coco_panoptic.py
Cellan/detectron2/data/datasets/lvis.py
Cellan/detectron2/data/datasets/lvis_v0_5_categories.py
Cellan/detectron2/data/datasets/lvis_v1_categories.py
Cellan/detectron2/data/datasets/lvis_v1_category_image_count.py
Cellan/detectron2/data/datasets/pascal_voc.py
Cellan/detectron2/data/datasets/register_coco.py
Cellan/detectron2/data/detection_utils.py
Cellan/detectron2/data/samplers/__init__.py
Cellan/detectron2/data/samplers/distributed_sampler.py
Cellan/detectron2/data/samplers/grouped_batch_sampler.py
Cellan/detectron2/data/transforms/__init__.py
Cellan/detectron2/data/transforms/augmentation.py
Cellan/detectron2/data/transforms/augmentation_impl.py
Cellan/detectron2/data/transforms/transform.py
Cellan/detectron2/engine/__init__.py
Cellan/detectron2/engine/defaults.py
Cellan/detectron2/engine/hooks.py
Cellan/detectron2/engine/launch.py
cellan-0.8.0.dist-info/METADATA
cellan-0.8.0.dist-info/WHEEL
cellan-0.8.0.dist-info/entry_points.txt
cellan-0.8.0.dist-info/licenses/LICENSE
cellan-0.8.0.dist-info/licenses/NOTICE.txt
cellan-0.8.0.dist-info/RECORD
