Metadata-Version: 2.1
Name: Cellan
Version: 0.8.0
Summary: Analyze cell images.
Keywords: Image analysis,Cell detection and classification,Pixel analysis
Author-Email: Yujia Hu <yujiahu415@gmail.com>
License: GPL-3.0
Classifier: License :: OSI Approved :: GNU General Public License v3 (GPLv3)
Classifier: Operating System :: OS Independent
Classifier: Programming Language :: Python :: 3
Classifier: Programming Language :: Python :: 3 :: Only
Classifier: Programming Language :: Python :: 3.9
Classifier: Programming Language :: Python :: 3.10
Classifier: Programming Language :: Python :: 3.11
Classifier: Programming Language :: Python :: 3.12
Classifier: Programming Language :: Python :: 3.13
Project-URL: Homepage, https://github.com/yujiahu415/Cellan
Requires-Python: >=3.9
Requires-Dist: numpy<=1.26.4
Requires-Dist: scipy
Requires-Dist: scikit-image
Requires-Dist: readlif
Requires-Dist: tifffile
Requires-Dist: imagecodecs
Requires-Dist: opencv-python
Requires-Dist: opencv-contrib-python
Requires-Dist: openpyxl
Requires-Dist: xlsxwriter
Requires-Dist: pandas
Requires-Dist: wxPython
Requires-Dist: packaging
Requires-Dist: requests
Requires-Dist: torch
Requires-Dist: torchvision
Requires-Dist: torchaudio
Requires-Dist: Pillow>=7.1
Requires-Dist: matplotlib
Requires-Dist: pycocotools>=2.0.2
Requires-Dist: termcolor>=1.1
Requires-Dist: yacs>=0.1.8
Requires-Dist: tabulate
Requires-Dist: cloudpickle
Requires-Dist: tqdm>4.29.0
Requires-Dist: tensorboard
Requires-Dist: fvcore<0.1.6,>=0.1.5
Requires-Dist: iopath>=0.1.7
Requires-Dist: dataclasses; python_version < "3.7"
Requires-Dist: omegaconf<2.4,>=2.1
Requires-Dist: hydra-core>=1.1
Requires-Dist: black
Requires-Dist: ninja
Requires-Dist: six
